telegramma/__init__.py
telegramma/__main__.py
telegramma/api/__init__.py
telegramma/api/_admin.py
telegramma/api/_config.py
telegramma/api/_database.py
telegramma/api/_logging.py
telegramma/api/_module.py
telegramma/api/_version.py
telegramma/core/__init__.py
telegramma/core/bot.py
telegramma/core/error_handler.py
telegramma/core/modules.py
telegramma/main.py
telegramma/modules/__init__.py
telegramma/modules/core/__module__.py
telegramma/modules/core/main.py
telegramma/modules/info/__module__.py
telegramma/modules/info/main.py
telegramma/modules/lineageos/__module__.py
telegramma/modules/lineageos/main.py
telegramma/modules/nekobin/__module__.py
telegramma/modules/nekobin/main.py
telegramma/modules/sed/__module__.py
telegramma/modules/sed/main.py
telegramma/modules/shell/__module__.py
telegramma/modules/shell/main.py
telegramma/modules/speedtest/__module__.py
telegramma/modules/speedtest/main.py
telegramma/modules/translate/__module__.py
telegramma/modules/translate/main.py
telegramma/modules/xda/__module__.py
telegramma/modules/xda/main.py
telegramma/modules/xda/words.py
telegramma-1.0.0.dist-info/WHEEL
telegramma-1.0.0.dist-info/METADATA
telegramma-1.0.0.dist-info/RECORD
