Metadata-Version: 2.1
Name: telegramma
Version: 1.0.0
Summary: Modular Telegram bot
Home-page: https://github.com/SebaUbuntu/telegramma
License: GPL-3.0-or-later
Author: Sebastiano Barezzi
Author-email: barezzisebastiano@gmail.com
Requires-Python: >=3.9,<4.0
Classifier: License :: OSI Approved :: GNU General Public License v3 or later (GPLv3+)
Classifier: Programming Language :: Python :: 3
Classifier: Programming Language :: Python :: 3.10
Classifier: Programming Language :: Python :: 3.9
Requires-Dist: python-telegram-bot (==20.0a0)
Requires-Dist: sebaubuntu-libs (>=1.0.6,<2.0.0)
Project-URL: Repository, https://github.com/SebaUbuntu/telegramma
